{"title":"Combined feed","url":"https://LIVESTREAM-KR.github.io/mcountdown/all.xml","elements":[{"title":"[2024 상반기 결산] 세븐틴(SEVENTEEN) - MAESTRO | Mnet 240725 방송 (엠카운트다운)","contents":"03:25","link":"https://tv.naver.com/v/58087723","retrieved":1721902528076},{"title":"[2024 상반기 결산] 아일릿(ILLIT) - Magnetic | Mnet 240725 방송 (엠카운트다운)","contents":"02:49","link":"https://tv.naver.com/v/58087377","retrieved":1721902528076},{"title":"[2024 상반기 결산] 투모로우바이투게더 (TOMORROW X TOGETHER) - Deja Vu | Mnet 240725 방송 (엠카운트다운)","contents":"02:57","link":"https://tv.naver.com/v/58087368","retrieved":1721902528076},{"title":"[2024 상반기 결산] LE SSERAFIM (르세라핌) - EASY | Mnet 240725 방송 (엠카운트다운)","contents":"02:49","link":"https://tv.naver.com/v/58087098","retrieved":1721902528077},{"title":"[2024 상반기 결산] (여자)아이들 ((G)I-DLE) - Super Lady | Mnet 240725 방송 (엠카운트다운)","contents":"03:22","link":"https://tv.naver.com/v/58086920","retrieved":1721902528080},{"title":"[2024 상반기 결산] NMIXX (엔믹스) - DASH | Mnet 240725 방송 (엠카운트다운)","contents":"02:57","link":"https://tv.naver.com/v/58086911","retrieved":1721902528081},{"title":"[2024 상반기 결산] aespa (에스파) - Supernova | Mnet 240725 방송 (엠카운트다운)","contents":"03:05","link":"https://tv.naver.com/v/58086351","retrieved":1721902528083},{"title":"[2024 상반기 결산] BABYMONSTER (베이비 몬스터) - SHEESH | Mnet 240725 방송 (엠카운트다운)","contents":"03:07","link":"https://tv.naver.com/v/58086142","retrieved":1721902528085},{"title":"[2024 상반기 결산] NCT DREAM (엔시티 드림) - Smoothie | Mnet 240725 방송 (엠카운트다운)","contents":"03:22","link":"https://tv.naver.com/v/58085828","retrieved":1721902528086},{"title":"[2024 상반기 결산] 비비(BIBI) - 밤양갱 | Mnet 240725 방송 (엠카운트다운)","contents":"02:30","link":"https://tv.naver.com/v/58085538","retrieved":1721902528087}]}